b_aws_cf/__init__.py
b_aws_cf/credentials.py
b_aws_cf/stack.py
b_aws_cf/stack_status.py
b_aws_cf/stacks.py
b_aws_cf/cli/__init__.py
b_aws_cf/cli/delete.py
b_aws_cf/cli/entry.py
b_aws_cf/exceptions/__init__.py
b_aws_cf/exceptions/stack_does_not_exist.py
b_aws_cf_fixtures/__init__.py
b_aws_cf_fixtures/stack_fixture.py
b_aws_cf_test/integration/__init__.py
b_aws_cf_test/integration/conftest.py
b_aws_cf_test/integration/tests/__init__.py
b_aws_cf_test/integration/tests/test_stack.py
b_aws_cf_test/integration/tests/test_stacks.py
b_aws_cf-0.2.1.dist-info/LICENSE
b_aws_cf-0.2.1.dist-info/METADATA
b_aws_cf-0.2.1.dist-info/WHEEL
b_aws_cf-0.2.1.dist-info/entry_points.txt
b_aws_cf-0.2.1.dist-info/top_level.txt
b_aws_cf-0.2.1.dist-info/RECORD
