Metadata-Version: 2.1
Name: b-aws-cf
Version: 0.2.1
Summary: Various utilities that wrap around boto3 for CloudFormation service.
Home-page: https://github.com/biomapas/B.AwsCf.git
Author: Laimonas Sutkus
Author-email: laimonas.sutkus@biomapas.com
License: Apache License 2.0
Keywords: AWS IAC CDK Parallel
Platform: UNKNOWN
Classifier: Programming Language :: Python :: 3
Classifier: Operating System :: OS Independent
Requires-Dist: boto3 (<=1.20.23,>=1.0.0)
Requires-Dist: pytest
